SketchyCV/__init__.py
SketchyCV/main.py
SketchyCV-1.1.0.dist-info/METADATA
SketchyCV-1.1.0.dist-info/WHEEL
SketchyCV-1.1.0.dist-info/top_level.txt
SketchyCV-1.1.0.dist-info/RECORD
