Metadata-Version: 2.1
Name: SketchyCV
Version: 1.1.0
